mksghpy/__init__.py
mksghpy/output.py
mksghpy/stringsplay.py
mksghpy-0.1.dist-info/METADATA
mksghpy-0.1.dist-info/WHEEL
mksghpy-0.1.dist-info/top_level.txt
mksghpy-0.1.dist-info/RECORD
